{
    "success":true,
    "data":{

        "articleList":[{
            "id":5,
            "title":"发现没有，很多成功人士几乎都不发朋友圈，这是为什么呢",
            "desc":"成功人士几乎都不发朋友圈这话还是有些片面，成功人士有很多种，有的是名人，有的是有钱人，虽然有名也会有钱但还是属于不同的成功人士。有名的成功人士其...",
            "imgUrl":"//upload-images.jianshu.io/upload_images/13253432-8a2ba26e7035fa89?imageMogr2/auto-orient/strip|imageView2/1/w/360/h/240"
        },
        {
            "id":6,
            "title":"移动开发还有未来吗？",
            "desc":"吃货作为一名资深的Android 开发者。从2017年下半年开始，就听到各种言论，例如“Android 开发凉凉”、“移动端开发没出路了赶紧转行...",
            "imgUrl":"//upload-images.jianshu.io/upload_images/16595031-f307d8c49f8380be.png?imageMogr2/auto-orient/strip|imageView2/1/w/360/h/240"
        },
        {
            "id":7,
            "title":"我投了接近50份简历，收到10个面试邀请，参与了5个面试，总结出了这篇。来自浙外一个无名专业不愿意透露姓名的我。如果非要有个署名，plz call me booming mango",
            "desc":"年前我辞去了接近7个月的第一份实习。 结束的时候心情很复杂。我很看好这家公司，且工作环境、工作氛围都是我所喜欢的，如果一直做下去，在应届毕业生中...",
            "imgUrl":"//upload-images.jianshu.io/upload_images/2600874-9360db4940c0d486.jpg?imageMogr2/auto-orient/strip|imageView2/1/w/360/h/240"
        },
        {
            "id":8,
            "title":"想做好PPT，你必须知道的12个技巧！",
            "desc":"想做好PPT，今天给大家总结一些方法，帮助大家提高制作PPT的效率。 01、PPT文件打不开 有时候会打不开PPT文件或总是出错，是怎么回事？ ...",
            "imgUrl":"//upload-images.jianshu.io/upload_images/5369363-58bb0b20525dc4c5.png?imageMogr2/auto-orient/strip|imageView2/1/w/360/h/240"
        }]
    
    }
}